src/__init__.py
src/arcgis_downloader.py
src/constants.py
src/download_item.py
src/downloader.py
src/tester.py
src/county_data_collectors/Charlotte.py
src/county_data_collectors/Lee.py
src/county_data_collectors/Manatee.py
src/county_data_collectors/Sarasota.py
src/county_data_collectors/__init__.py
src/county_data_collectors/base_collector.py
src/county_data_collectors/county_mapper.py
parcel_data_collector2-1.2.dist-info/LICENSE
parcel_data_collector2-1.2.dist-info/METADATA
parcel_data_collector2-1.2.dist-info/WHEEL
parcel_data_collector2-1.2.dist-info/top_level.txt
parcel_data_collector2-1.2.dist-info/RECORD
