Metadata-Version: 2.1
Name: parcel-data-collector2
Version: 1.2
Summary: UNKNOWN
Home-page: UNKNOWN
License: MIT
Platform: UNKNOWN
License-File: LICENSE
Requires-Dist: aiofiles ==22.1.0
Requires-Dist: aiosqlite ==0.19.0
Requires-Dist: anyio ==3.7.1
Requires-Dist: argon2-cffi ==23.1.0
Requires-Dist: argon2-cffi-bindings ==21.2.0
Requires-Dist: arrow ==1.2.3
Requires-Dist: asttokens ==2.2.1
Requires-Dist: asyncio ==3.4.3
Requires-Dist: attrs ==23.1.0
Requires-Dist: Babel ==2.12.1
Requires-Dist: backcall ==0.2.0
Requires-Dist: beautifulsoup4 ==4.12.2
Requires-Dist: bleach ==6.0.0
Requires-Dist: cachetools ==5.3.1
Requires-Dist: certifi ==2023.7.22
Requires-Dist: cffi ==1.15.1
Requires-Dist: charset-normalizer ==3.2.0
Requires-Dist: click ==8.1.7
Requires-Dist: cloudpickle ==2.2.1
Requires-Dist: colorama ==0.4.6
Requires-Dist: comm ==0.1.4
Requires-Dist: contourpy ==1.1.0
Requires-Dist: cryptography ==41.0.3
Requires-Dist: cycler ==0.11.0
Requires-Dist: dask ==2023.8.1
Requires-Dist: debugpy ==1.6.7.post1
Requires-Dist: decorator ==5.1.1
Requires-Dist: defusedxml ==0.7.1
Requires-Dist: docutils ==0.20.1
Requires-Dist: et-xmlfile ==1.1.0
Requires-Dist: exceptiongroup ==1.1.3
Requires-Dist: executing ==1.2.0
Requires-Dist: fastjsonschema ==2.18.0
Requires-Dist: fonttools ==4.42.1
Requires-Dist: fqdn ==1.5.1
Requires-Dist: fsspec ==2023.6.0
Requires-Dist: geomet ==1.0.0
Requires-Dist: gssapi ==1.8.2
Requires-Dist: idna ==3.4
Requires-Dist: importlib-metadata ==6.8.0
Requires-Dist: importlib-resources ==6.0.1
Requires-Dist: ipykernel ==6.25.1
Requires-Dist: ipython ==8.14.0
Requires-Dist: ipython-genutils ==0.2.0
Requires-Dist: ipywidgets ==8.1.0
Requires-Dist: isoduration ==20.11.0
Requires-Dist: jaraco.classes ==3.3.0
Requires-Dist: jedi ==0.19.0
Requires-Dist: Jinja2 ==3.1.2
Requires-Dist: json5 ==0.9.14
Requires-Dist: jsonpointer ==2.4
Requires-Dist: jsonschema ==4.19.0
Requires-Dist: jsonschema-specifications ==2023.7.1
Requires-Dist: jupyter-client ==6.1.12
Requires-Dist: jupyter-events ==0.7.0
Requires-Dist: jupyter-server ==1.24.0
Requires-Dist: jupyter-ydoc ==0.2.5
Requires-Dist: jupyter-core ==5.3.1
Requires-Dist: jupyter-server-fileid ==0.9.0
Requires-Dist: jupyter-server-ydoc ==0.8.0
Requires-Dist: jupyterlab ==3.6.5
Requires-Dist: jupyterlab-pygments ==0.2.2
Requires-Dist: jupyterlab-widgets ==3.0.8
Requires-Dist: jupyterlab-server ==2.24.0
Requires-Dist: keyring ==24.2.0
Requires-Dist: kiwisolver ==1.4.4
Requires-Dist: lerc ==4.0.1
Requires-Dist: locket ==1.0.0
Requires-Dist: lxml ==4.9.3
Requires-Dist: markdown-it-py ==3.0.0
Requires-Dist: MarkupSafe ==2.1.3
Requires-Dist: matplotlib ==3.7.2
Requires-Dist: matplotlib-inline ==0.1.6
Requires-Dist: mdurl ==0.1.2
Requires-Dist: mistune ==3.0.1
Requires-Dist: more-itertools ==10.1.0
Requires-Dist: nbclassic ==1.0.0
Requires-Dist: nbclient ==0.8.0
Requires-Dist: nbconvert ==7.7.4
Requires-Dist: nbformat ==5.9.2
Requires-Dist: nest-asyncio ==1.5.7
Requires-Dist: notebook ==6.5.5
Requires-Dist: notebook-shim ==0.2.3
Requires-Dist: numpy ==1.25.2
Requires-Dist: oauthlib ==3.2.2
Requires-Dist: openpyxl ==3.1.2
Requires-Dist: packaging ==23.1
Requires-Dist: pandas ==2.0.3
Requires-Dist: pandocfilters ==1.5.0
Requires-Dist: parso ==0.8.3
Requires-Dist: partd ==1.4.0
Requires-Dist: pickleshare ==0.7.5
Requires-Dist: Pillow ==10.0.0
Requires-Dist: pkginfo ==1.9.6
Requires-Dist: platformdirs ==3.10.0
Requires-Dist: prometheus-client ==0.17.1
Requires-Dist: prompt-toolkit ==3.0.39
Requires-Dist: psutil ==5.9.5
Requires-Dist: pure-eval ==0.2.2
Requires-Dist: pyarrow ==13.0.0
Requires-Dist: pycparser ==2.21
Requires-Dist: Pygments ==2.16.1
Requires-Dist: pyparsing ==3.0.9
Requires-Dist: pypiwin32 ==223
Requires-Dist: pyshp ==2.3.1
Requires-Dist: pyspnego ==0.9.1
Requires-Dist: python-certifi-win32 ==1.6.1
Requires-Dist: python-dateutil ==2.8.2
Requires-Dist: python-dotenv ==1.0.0
Requires-Dist: python-json-logger ==2.0.7
Requires-Dist: pytz ==2023.3
Requires-Dist: pywin32 ==306
Requires-Dist: pywin32-ctypes ==0.2.2
Requires-Dist: pywinpty ==2.0.11
Requires-Dist: PyYAML ==6.0.1
Requires-Dist: pyzmq ==24.0.1
Requires-Dist: readme-renderer ==41.0
Requires-Dist: referencing ==0.30.2
Requires-Dist: requests ==2.31.0
Requires-Dist: requests-gssapi ==1.2.3
Requires-Dist: requests-kerberos ==0.14.0
Requires-Dist: requests-negotiate-sspi ==0.5.2
Requires-Dist: requests-oauthlib ==1.3.1
Requires-Dist: requests-toolbelt ==1.0.0
Requires-Dist: rfc3339-validator ==0.1.4
Requires-Dist: rfc3986 ==2.0.0
Requires-Dist: rfc3986-validator ==0.1.1
Requires-Dist: rich ==13.5.2
Requires-Dist: rpds-py ==0.9.2
Requires-Dist: Send2Trash ==1.8.2
Requires-Dist: setuptools-scm ==7.1.0
Requires-Dist: six ==1.16.0
Requires-Dist: sniffio ==1.3.0
Requires-Dist: soupsieve ==2.4.1
Requires-Dist: stack-data ==0.6.2
Requires-Dist: terminado ==0.17.1
Requires-Dist: tinycss2 ==1.2.1
Requires-Dist: tomli ==2.0.1
Requires-Dist: toolz ==0.12.0
Requires-Dist: tornado ==6.3.3
Requires-Dist: traitlets ==5.9.0
Requires-Dist: twine ==4.0.2
Requires-Dist: typing-extensions ==4.7.1
Requires-Dist: tzdata ==2023.3
Requires-Dist: ujson ==5.8.0
Requires-Dist: uri-template ==1.3.0
Requires-Dist: urllib3 ==1.26.0
Requires-Dist: wcwidth ==0.2.6
Requires-Dist: webcolors ==1.13
Requires-Dist: webencodings ==0.5.1
Requires-Dist: websocket-client ==1.6.2
Requires-Dist: widgetsnbextension ==4.0.8
Requires-Dist: winkerberos ==0.9.1
Requires-Dist: wrapt ==1.15.0
Requires-Dist: y-py ==0.6.0
Requires-Dist: ypy-websocket ==0.8.4
Requires-Dist: zipp ==3.16.2
